<?xml version="1.0" encoding="UTF-8"?>
<units>
	<infantry>
		<unit id="1" name="Swordsman">
			<era>1 2 3 4 5 6</era>
			<health>1024</health>
			<range>1</range>
			<attack>128</attack>
			<speed>Average</speed>
			<stance>aggressive</stance>
			<class>melee</class>
		</unit>
		<unit id="2" name="Barbarian">
			<era>1 2 3 4 5 6</era>
			<health>768</health>
			<range>1</range>
			<attack>128</attack>
			<speed>Average</speed>
			<stance>aggressive</stance>
			<class>melee</class>
		</unit>
	</infantry>
	<armed>
		<unit id="1" name="Ballista">
			<era>3 4 5 6</era>
			<health>2048</health>
			<range>100</range>
			<attack>256</attack>
			<speed>slow</speed>
			<stance>passive</stance>
			<class>besiegement</class>
		</unit>
	</armed>
	<marine>
		<unit id="1" name="Galley">
			<era>3 4 5 6 7 8</era>
			<health>4096</health>
			<range>75</range>
			<attack>384</attack>
			<speed>slow</speed>
			<stance>aggressive</stance>
			<class>naval</class>
		</unit>
	</marine>
	<airforce>
		<unit id="1" name="FokkerDR1">
			<era>9 10</era>
			<health>128</health>
			<range>75</range>
			<attack>128</attack>
			<speed>fast</speed>
			<stance>aggressive</stance>
			<class>fighter</class>
		</unit>
	</airforce>
</units>
